setup.py
sudden_appearance_tictactoe/Game.py
sudden_appearance_tictactoe/Grid.py
sudden_appearance_tictactoe/O.py
sudden_appearance_tictactoe/X.py
sudden_appearance_tictactoe.egg-info/PKG-INFO
sudden_appearance_tictactoe.egg-info/SOURCES.txt
sudden_appearance_tictactoe.egg-info/dependency_links.txt
sudden_appearance_tictactoe.egg-info/entry_points.txt
sudden_appearance_tictactoe.egg-info/not-zip-safe
sudden_appearance_tictactoe.egg-info/requires.txt
sudden_appearance_tictactoe.egg-info/top_level.txt